[
    {
        "id": "3051371017",
        "ad_type": "offer",
        "car_km": "40000 ",
        "car_registration": " 11/2019",
        "image_src": "https://img.kleinanzeigen.de/api/v1/prod-ads/images/d8/d8a4a781-ddee-49de-acc7-564917b1efb4?rule=$_2.AUTO",
        "location": "42855 Remscheid",
        "date_posted": "",
        "date_scrape": "04/08/2025",
        "title": "Dacia Duster 4x4*LED*Garantie*AHK*Android*8Fach*uvm",
        "price": "18500 \u20ac VB"
    },
    {
        "id": "2963386189",
        "ad_type": "wanted",
        "car_km": "200000 ",
        "car_registration": " 01/2011",
        "image_src": "https://img.kleinanzeigen.de/api/v1/prod-ads/images/34/3498c2bd-df30-4609-88e2-8e775621ac5a?rule=$_2.AUTO",
        "location": "49084 Osnabr\u00fcck",
        "date_posted": "",
        "date_scrape": "04/08/2025",
        "title": "Motorschaden Ankauf Dacia Duster Sandero Dokker Lodgy joger logan",
        "price": "4250 \u20ac VB"
    },
    {
        "id": "3051249946",
        "ad_type": "offer",
        "car_km": "108500 ",
        "car_registration": " 09/2012",
        "image_src": "https://img.kleinanzeigen.de/api/v1/prod-ads/images/4d/4dc46d9b-9469-4fe7-bda4-2fa76aa9776a?rule=$_2.AUTO",
        "location": "81827 Trudering-\u200bRiem",
        "date_posted": "Gestern, 13:58",
        "date_scrape": "04/08/2025",
        "title": "Dacia Logan",
        "price": "3400 \u20ac VB"
    },
    {
        "id": "3051240482",
        "ad_type": "offer",
        "car_km": "94000 ",
        "car_registration": " 07/2018",
        "image_src": "https://img.kleinanzeigen.de/api/v1/prod-ads/images/df/df5d493e-6306-4a0f-9838-de2e4a9ab7bf?rule=$_2.AUTO",
        "location": "76646 Bruchsal",
        "date_posted": "Gestern, 13:48",
        "date_scrape": "04/08/2025",
        "title": "Dacia Logan MCV II *2.Hand*guter Zustand",
        "price": "4600 "
    },
    {
        "id": "3051238908",
        "ad_type": "offer",
        "car_km": "34911 ",
        "car_registration": " 07/2020",
        "image_src": "https://img.kleinanzeigen.de/api/v1/prod-ads/images/85/85c96da0-047f-436f-b922-25eccf294dab?rule=$_2.AUTO",
        "location": "01156 Altfranken",
        "date_posted": "Gestern, 13:47",
        "date_scrape": "04/08/2025",
        "title": "Dacia Duster TCe 100 ECO-G 2WD Celebration",
        "price": "13980 "
    },
    {
        "id": "3051236359",
        "ad_type": "offer",
        "car_km": "72000 ",
        "car_registration": " 10/2017",
        "image_src": "https://img.kleinanzeigen.de/api/v1/prod-ads/images/cb/cba10f3f-698c-4d64-b8bc-744bdb3ad43f?rule=$_2.AUTO",
        "location": "48653 Coesfeld",
        "date_posted": "Gestern, 13:44",
        "date_scrape": "04/08/2025",
        "title": "Dacia Lodgy Ambiance 7 Sitzer _Bestzustand_",
        "price": "10777 "
    },
    {
        "id": "3051228007",
        "ad_type": "offer",
        "car_km": "139000 ",
        "car_registration": " 07/2010",
        "image_src": "https://img.kleinanzeigen.de/api/v1/prod-ads/images/56/56d1d4f6-7ba7-48bd-9756-ceff76ffc996?rule=$_2.AUTO",
        "location": "66809 Nalbach",
        "date_posted": "Gestern, 13:36",
        "date_scrape": "04/08/2025",
        "title": "Dacia Duster 1.6 16V 105 4x2 Ambiance Ambiance",
        "price": "5400 "
    },
    {
        "id": "3051227531",
        "ad_type": "offer",
        "car_km": "40490 ",
        "car_registration": " 12/2018",
        "image_src": "https://img.kleinanzeigen.de/api/v1/prod-ads/images/cd/cd14381b-8280-4795-abce-7dcce8087b4f?rule=$_2.AUTO",
        "location": "13467 Reinickendorf",
        "date_posted": "Gestern, 13:35",
        "date_scrape": "04/08/2025",
        "title": "Dacia Sandero Stepway Celebration Kamera Tempomat Navi",
        "price": "10980 "
    },
    {
        "id": "3051225451",
        "ad_type": "offer",
        "car_km": "97959 ",
        "car_registration": " 05/2009",
        "image_src": "https://img.kleinanzeigen.de/api/v1/prod-ads/images/e5/e5ec0279-ccb5-47dc-9347-4e2d413a124b?rule=$_2.AUTO",
        "location": "44894 Bochum-\u200bOst",
        "date_posted": "Gestern, 13:33",
        "date_scrape": "04/08/2025",
        "title": "Dacia Sandero Ambiance",
        "price": "2971 "
    },
    {
        "id": "3051224802",
        "ad_type": "offer",
        "car_km": "75000 ",
        "car_registration": " 04/2013",
        "image_src": "https://img.kleinanzeigen.de/api/v1/prod-ads/images/e0/e04d1f04-4fca-4ea9-8353-17fd09431262?rule=$_2.AUTO",
        "location": "51069 K\u00f6ln Dellbr\u00fcck",
        "date_posted": "Gestern, 13:32",
        "date_scrape": "04/08/2025",
        "title": "123578664435",
        "price": "3000 "
    },
    {
        "id": "3051222993",
        "ad_type": "offer",
        "car_km": "117000 ",
        "car_registration": " 04/2013",
        "image_src": "https://img.kleinanzeigen.de/api/v1/prod-ads/images/45/45024829-266a-4214-b17e-baa7ef5b240a?rule=$_2.AUTO",
        "location": "50769 F\u00fchlingen",
        "date_posted": "Gestern, 13:30",
        "date_scrape": "04/08/2025",
        "title": "Dacia Sandero Stepway",
        "price": "3900 \u20ac VB"
    },
    {
        "id": "3051219227",
        "ad_type": "offer",
        "car_km": "16359 ",
        "car_registration": " 03/2022",
        "image_src": "https://img.kleinanzeigen.de/api/v1/prod-ads/images/bb/bb7d307f-5ae9-437d-8c8a-d62751a95992?rule=$_2.AUTO",
        "location": "60314 Ostend",
        "date_posted": "Gestern, 13:27",
        "date_scrape": "04/08/2025",
        "title": "Dacia Duster EXTREME TCe 130 2WD",
        "price": "18690 "
    },
    {
        "id": "3051219142",
        "ad_type": "offer",
        "car_km": "182000 ",
        "car_registration": " 04/2009",
        "image_src": "https://img.kleinanzeigen.de/api/v1/prod-ads/images/e7/e75c89b4-0e2c-473d-809e-a00b1431241f?rule=$_2.AUTO",
        "location": "48683 Ahaus",
        "date_posted": "Gestern, 13:27",
        "date_scrape": "04/08/2025",
        "title": "Dacia Sandero",
        "price": "1700 \u20ac VB"
    },
    {
        "id": "3051218138",
        "ad_type": "offer",
        "car_km": "136007 ",
        "car_registration": " 07/2016",
        "image_src": "https://img.kleinanzeigen.de/api/v1/prod-ads/images/5b/5bda90d6-1084-4998-8523-7e8dc28c58f7?rule=$_2.AUTO",
        "location": "06796 Brehna",
        "date_posted": "Gestern, 13:26",
        "date_scrape": "04/08/2025",
        "title": "Dacia Sandero II 1.5 dCi Stepway Prestige",
        "price": "6999 "
    },
    {
        "id": "3051210202",
        "ad_type": "wanted",
        "car_km": "150000 ",
        "car_registration": " 05/2015",
        "image_src": "https://img.kleinanzeigen.de/api/v1/prod-ads/images/6b/6be69608-d416-492a-8b08-87773e356e9a?rule=$_2.AUTO",
        "location": "10997 Kreuzberg",
        "date_posted": "Gestern, 13:24",
        "date_scrape": "04/08/2025",
        "title": "Motorschaden Ankauf Renault Dacia BMW Audi Ford Vw Hyundai Seat",
        "price": "VB"
    },
    {
        "id": "3051216052",
        "ad_type": "offer",
        "car_km": "17500 ",
        "car_registration": " 08/2022",
        "image_src": "https://img.kleinanzeigen.de/api/v1/prod-ads/images/7e/7ed79dd1-fb85-47a3-8c87-b4410389c810?rule=$_2.AUTO",
        "location": "72770 Reutlingen",
        "date_posted": "Gestern, 13:23",
        "date_scrape": "04/08/2025",
        "title": "Dacia Sandero Stepway TCe 90 Comfort",
        "price": "13930 "
    },
    {
        "id": "2963386189",
        "ad_type": "wanted",
        "car_km": "200000 ",
        "car_registration": " 01/2011",
        "image_src": "https://img.kleinanzeigen.de/api/v1/prod-ads/images/34/3498c2bd-df30-4609-88e2-8e775621ac5a?rule=$_2.AUTO",
        "location": "49084 Osnabr\u00fcck",
        "date_posted": "Gestern, 13:22",
        "date_scrape": "04/08/2025",
        "title": "Motorschaden Ankauf Dacia Duster Sandero Dokker Lodgy joger logan",
        "price": "4250 \u20ac VB"
    },
    {
        "id": "3051213487",
        "ad_type": "offer",
        "car_km": "61400 ",
        "car_registration": " 06/2017",
        "image_src": "https://img.kleinanzeigen.de/api/v1/prod-ads/images/01/01e9b5de-24ea-4cce-b2fb-a46d3099190a?rule=$_2.AUTO",
        "location": "93047 Regensburg",
        "date_posted": "Gestern, 13:21",
        "date_scrape": "04/08/2025",
        "title": "Dacia Sandero 1.0  T\u00dcV 8/26  Top Zustand !!!",
        "price": "4300 \u20ac VB"
    },
    {
        "id": "3051204318",
        "ad_type": "offer",
        "car_km": "130000 ",
        "car_registration": " 11/2009",
        "image_src": "https://img.kleinanzeigen.de/api/v1/prod-ads/images/9e/9ed9d6ed-77e9-4c48-bf13-df409f972fc2?rule=$_2.AUTO",
        "location": "69469 Weinheim",
        "date_posted": "Gestern, 13:11",
        "date_scrape": "04/08/2025",
        "title": "Dacia Sandero 2009, 1,4 mpi, T\u00fcv bis 2026",
        "price": "2150 "
    },
    {
        "id": "3051201434",
        "ad_type": "offer",
        "car_km": "58000 ",
        "car_registration": " 07/2018",
        "image_src": "https://img.kleinanzeigen.de/api/v1/prod-ads/images/15/15189d07-2d4e-49f4-ba87-7af1041e80ca?rule=$_2.AUTO",
        "location": "34396 Liebenau",
        "date_posted": "Gestern, 13:08",
        "date_scrape": "04/08/2025",
        "title": "Dacia Duster SCe 115 4x2 Comfort Comfort",
        "price": "12500 "
    },
    {
        "id": "3051198091",
        "ad_type": "offer",
        "car_km": "17000 ",
        "car_registration": " 06/2022",
        "image_src": "https://img.kleinanzeigen.de/api/v1/prod-ads/images/18/188ff795-52f8-494e-9465-548aafea5485?rule=$_2.AUTO",
        "location": "46049 Oberhausen",
        "date_posted": "Gestern, 13:05",
        "date_scrape": "04/08/2025",
        "title": "Dacia Jogger TCe 110 Extreme+ NAVI PDC SHZ KLIMAAUT.",
        "price": "20490 "
    },
    {
        "id": "3051195631",
        "ad_type": "offer",
        "car_km": "137500 ",
        "car_registration": " 08/2014",
        "image_src": "https://img.kleinanzeigen.de/api/v1/prod-ads/images/66/66c61466-4246-4a72-82cc-55ad3b459383?rule=$_2.AUTO",
        "location": "41836 H\u00fcckelhoven",
        "date_posted": "Gestern, 13:03",
        "date_scrape": "04/08/2025",
        "title": "Dacia Duster LPG Prestige",
        "price": "7990 "
    },
    {
        "id": "3051193917",
        "ad_type": "offer",
        "car_km": "115000 ",
        "car_registration": " 01/2017",
        "image_src": "https://img.kleinanzeigen.de/api/v1/prod-ads/images/6d/6d25372b-b1be-4b48-87d7-ed6b014a27f9?rule=$_2.AUTO",
        "location": "45884 Gelsenkirchen",
        "date_posted": "Gestern, 13:01",
        "date_scrape": "04/08/2025",
        "title": "Dacia Duster 1.2 Benzin",
        "price": "4750 "
    },
    {
        "id": "3051189192",
        "ad_type": "offer",
        "car_km": "107551 ",
        "car_registration": " 08/2009",
        "image_src": "https://img.kleinanzeigen.de/api/v1/prod-ads/images/45/45ff2a1d-e139-4e09-a071-f5315fa9de05?rule=$_2.AUTO",
        "location": "21337 L\u00fcneburg",
        "date_posted": "Gestern, 12:56",
        "date_scrape": "04/08/2025",
        "title": "Dacia Logan MCV 1,4 MPI Servo*ZV*AHK",
        "price": "2000 \u20ac VB"
    },
    {
        "id": "3051182722",
        "ad_type": "offer",
        "car_km": "0 ",
        "car_registration": " 04/2025",
        "image_src": "https://img.kleinanzeigen.de/api/v1/prod-ads/images/9e/9e0c3d2d-0150-4b05-96f9-aa48cfca7d64?rule=$_2.AUTO",
        "location": "52538 Gangelt",
        "date_posted": "Gestern, 12:50",
        "date_scrape": "04/08/2025",
        "title": "Dacia Sandero Stepway Extreme",
        "price": "19285 "
    },
    {
        "id": "3051181761",
        "ad_type": "offer",
        "car_km": "41675 ",
        "car_registration": " 12/2018",
        "image_src": "https://img.kleinanzeigen.de/api/v1/prod-ads/images/e7/e767deeb-fabe-438c-8230-1a62a64e750c?rule=$_2.AUTO",
        "location": "52379 Langerwehe",
        "date_posted": "Gestern, 12:49",
        "date_scrape": "04/08/2025",
        "title": "Dacia Sandero II Essential*AHK*klima*1.Hand*",
        "price": "8499 "
    },
    {
        "id": "3051181469",
        "ad_type": "offer",
        "car_km": "44102 ",
        "car_registration": " 02/2020",
        "image_src": "https://img.kleinanzeigen.de/api/v1/prod-ads/images/3f/3f1c4fc9-88d7-4c64-97e7-b5519bf51a0e?rule=$_2.AUTO",
        "location": "51067 K\u00f6ln Buchheim",
        "date_posted": "Gestern, 12:49",
        "date_scrape": "04/08/2025",
        "title": "Dacia Logan MCV II Kombi 1,0 Essential/Nur 44.000km",
        "price": "9590 "
    }
]