[
    {
        "id": "3099942354",
        "ad_type": "offer",
        "car_km": "158700 ",
        "car_registration": " 07/2012",
        "image_src": "https://img.kleinanzeigen.de/api/v1/prod-ads/images/c4/c4759628-ac76-4afc-a679-fff1ed1cbeec?rule=$_2.AUTO",
        "location": "73278 Schlierbach",
        "date_posted": "01.06.2025",
        "date_scrape": "06/08/2025",
        "title": "Dacia Lodgy Laureate",
        "price": "2390 "
    },
    {
        "id": "3099915948",
        "ad_type": "offer",
        "car_km": "63595 ",
        "car_registration": " 07/2019",
        "image_src": "https://img.kleinanzeigen.de/api/v1/prod-ads/images/49/49ebabde-cf1e-437d-aab6-9fc0e2566caa?rule=$_2.AUTO",
        "location": "72184 Eutingen",
        "date_posted": "01.06.2025",
        "date_scrape": "06/08/2025",
        "title": "Dacia Duster TCe 150 4\u00d72WD GPF Adventure Adventure",
        "price": "15800 "
    },
    {
        "id": "3099850683",
        "ad_type": "offer",
        "car_km": "67000 ",
        "car_registration": " 12/2016",
        "image_src": "https://img.kleinanzeigen.de/api/v1/prod-ads/images/27/271eb7d3-49c0-4e83-9351-f3457b9aef83?rule=$_2.AUTO",
        "location": "73249 Wernau",
        "date_posted": "01.06.2025",
        "date_scrape": "06/08/2025",
        "title": "Dacia Lodgy 7 Sitzer",
        "price": "9700 "
    },
    {
        "id": "3099765819",
        "ad_type": "offer",
        "car_km": "115000 ",
        "car_registration": " 06/2006",
        "image_src": "https://img.kleinanzeigen.de/api/v1/prod-ads/images/58/58c68415-7396-4764-8e8b-9926487439ed?rule=$_2.AUTO",
        "location": "78661 Dietingen",
        "date_posted": "01.06.2025",
        "date_scrape": "06/08/2025",
        "title": "Dacia Logan 1.5 dci! T\u00fcv Neu",
        "price": "2500 \u20ac VB"
    },
    {
        "id": "3099678104",
        "ad_type": "offer",
        "car_km": "18900 ",
        "car_registration": " 05/2024",
        "image_src": "https://img.kleinanzeigen.de/api/v1/prod-ads/images/06/067fbcb7-cd7e-40b7-bbbf-b4e6eb4d20de?rule=$_2.AUTO",
        "location": "72516 Scheer",
        "date_posted": "01.06.2025",
        "date_scrape": "06/08/2025",
        "title": "Dacia Sandero TCe 90 Expression Expression",
        "price": "14300 "
    },
    {
        "id": "3099658551",
        "ad_type": "offer",
        "car_km": "48825 ",
        "car_registration": " 03/2020",
        "image_src": "https://img.kleinanzeigen.de/api/v1/prod-ads/images/22/229a4a48-7f0e-4a73-b14e-775717dec8d4?rule=$_2.AUTO",
        "location": "78234 Engen",
        "date_posted": "01.06.2025",
        "date_scrape": "06/08/2025",
        "title": "Dacia Sandero SCe 75 Access Access",
        "price": "9299 "
    },
    {
        "id": "3099353448",
        "ad_type": "offer",
        "car_km": "150000 ",
        "car_registration": " 07/2016",
        "image_src": "https://img.kleinanzeigen.de/api/v1/prod-ads/images/65/6513e6a1-5381-4c90-88bd-1a6c02f1f692?rule=$_2.AUTO",
        "location": "88410 Bad Wurzach",
        "date_posted": "01.06.2025",
        "date_scrape": "06/08/2025",
        "title": "Dacia Sandero II Ambiance-Klima-elektr.Fensterh",
        "price": "3700 "
    },
    {
        "id": "3099347425",
        "ad_type": "offer",
        "car_km": "88000 ",
        "car_registration": " 03/2016",
        "image_src": "https://img.kleinanzeigen.de/api/v1/prod-ads/images/3a/3ad555f4-a8b3-483a-a70d-85aa874a2ada?rule=$_2.AUTO",
        "location": "88410 Bad Wurzach",
        "date_posted": "01.06.2025",
        "date_scrape": "06/08/2025",
        "title": "Dacia Sandero II Stepway Ambiance-8800km-Klima-EURO6",
        "price": "5800 "
    },
    {
        "id": "3099288543",
        "ad_type": "offer",
        "car_km": "45890 ",
        "car_registration": " 02/2023",
        "image_src": "https://img.kleinanzeigen.de/api/v1/prod-ads/images/2b/2bbf04b1-b3f4-44ee-b351-23cf089b9cb4?rule=$_2.AUTO",
        "location": "72401 Haigerloch",
        "date_posted": "01.06.2025",
        "date_scrape": "06/08/2025",
        "title": "Dacia Sandero 3",
        "price": "10500 \u20ac VB"
    },
    {
        "id": "3068414283",
        "ad_type": "offer",
        "car_km": "106000 ",
        "car_registration": " 02/2019",
        "image_src": "https://img.kleinanzeigen.de/api/v1/prod-ads/images/3d/3d856d6b-1c21-4435-92c7-9e400341fb18?rule=$_2.AUTO",
        "location": "73312 Geislingen an der Steige",
        "date_posted": "01.06.2025",
        "date_scrape": "06/08/2025",
        "title": "Dacia Sandero , 1-HAND*EURO6",
        "price": "3650 "
    },
    {
        "id": "3099164789",
        "ad_type": "offer",
        "car_km": "257500 ",
        "car_registration": " 12/2016",
        "image_src": "https://img.kleinanzeigen.de/api/v1/prod-ads/images/92/9261be91-a8b0-443f-ad4f-27cbfed0254f?rule=$_2.AUTO",
        "location": "73035 G\u00f6ppingen",
        "date_posted": "01.06.2025",
        "date_scrape": "06/08/2025",
        "title": "Dacia Sandero II Ambiance Navi Automatic",
        "price": "5399 "
    },
    {
        "id": "3099159415",
        "ad_type": "offer",
        "car_km": "170000 ",
        "car_registration": " 03/2007",
        "image_src": "https://img.kleinanzeigen.de/api/v1/prod-ads/images/82/82c166ca-4bda-4da6-a431-86423a3f18de?rule=$_2.AUTO",
        "location": "74074 Heilbronn",
        "date_posted": "01.06.2025",
        "date_scrape": "06/08/2025",
        "title": "Dacia Logan T\u00dcV 06/26",
        "price": "900 "
    },
    {
        "id": "3099144084",
        "ad_type": "offer",
        "car_km": "10430 ",
        "car_registration": " 09/2024",
        "image_src": "https://img.kleinanzeigen.de/api/v1/prod-ads/images/e9/e9214df1-1d86-447d-b817-7f3f7efaf779?rule=$_2.AUTO",
        "location": "88662 \u00dcberlingen",
        "date_posted": "01.06.2025",
        "date_scrape": "06/08/2025",
        "title": "Dacia Sandero Essential SCe 65 Klima sofort lieferbar",
        "price": "14399 "
    },
    {
        "id": "3099143370",
        "ad_type": "offer",
        "car_km": "8999 ",
        "car_registration": " 09/2024",
        "image_src": "https://img.kleinanzeigen.de/api/v1/prod-ads/images/5b/5b4fcea8-9fd0-44e5-8687-b8bb136c4a2d?rule=$_2.AUTO",
        "location": "74076 Heilbronn",
        "date_posted": "01.06.2025",
        "date_scrape": "06/08/2025",
        "title": "Dacia Sandero Stepway Expression TCE 90-CVT Klima",
        "price": "18660 "
    },
    {
        "id": "3099132429",
        "ad_type": "offer",
        "car_km": "18854 ",
        "car_registration": " 12/2022",
        "image_src": "https://img.kleinanzeigen.de/api/v1/prod-ads/images/0b/0b1fefd0-b59f-419d-b42d-8b28602a7c2b?rule=$_2.AUTO",
        "location": "88213 Ravensburg",
        "date_posted": "31.05.2025",
        "date_scrape": "06/08/2025",
        "title": "DACIA SPRING ESSENTIAL ELEKTRIC mit GARANTIE !!!",
        "price": "10500 \u20ac VB"
    },
    {
        "id": "3099051390",
        "ad_type": "offer",
        "car_km": "131000 ",
        "car_registration": " 07/2012",
        "image_src": "https://img.kleinanzeigen.de/api/v1/prod-ads/images/4e/4e82a11e-2329-4763-accf-136939dec373?rule=$_2.AUTO",
        "location": "97877 Wertheim",
        "date_posted": "31.05.2025",
        "date_scrape": "06/08/2025",
        "title": "Dacia Sondero",
        "price": "1800 \u20ac VB"
    },
    {
        "id": "3098782906",
        "ad_type": "offer",
        "car_km": "108000 ",
        "car_registration": " 07/2020",
        "image_src": "https://img.kleinanzeigen.de/api/v1/prod-ads/images/f1/f17e30c3-febe-4d09-8464-e4076bc54d6b?rule=$_2.AUTO",
        "location": "77880 Sasbach",
        "date_posted": "31.05.2025",
        "date_scrape": "06/08/2025",
        "title": "Dacia Dokker Stepway/Garantie/Scheckheft",
        "price": "13499 "
    },
    {
        "id": "3098775361",
        "ad_type": "offer",
        "car_km": "123305 ",
        "car_registration": " 01/2009",
        "image_src": "https://img.kleinanzeigen.de/api/v1/prod-ads/images/98/987c8501-f2ca-49c3-88ed-edf43dd8f0be?rule=$_2.AUTO",
        "location": "77886 Lauf",
        "date_posted": "31.05.2025",
        "date_scrape": "06/08/2025",
        "title": "Dacia Logan 1.4 - AHK, T\u00dcV bis 2027 \"Rostfrei\"",
        "price": "2500 "
    },
    {
        "id": "3098748960",
        "ad_type": "offer",
        "car_km": "1500 ",
        "car_registration": " 11/2023",
        "image_src": "https://img.kleinanzeigen.de/api/v1/prod-ads/images/a2/a2546eea-f65c-464e-af4d-9f116a304fe0?rule=$_2.AUTO",
        "location": "79114 Freiburg im Breisgau",
        "date_posted": "31.05.2025",
        "date_scrape": "06/08/2025",
        "title": "Dacia Jogger Neu ,5 Sitzer",
        "price": "19600 "
    },
    {
        "id": "3098660686",
        "ad_type": "offer",
        "car_km": "78000 ",
        "car_registration": " 03/2015",
        "image_src": "https://img.kleinanzeigen.de/api/v1/prod-ads/images/5d/5d92f2f8-3a09-43ba-91aa-cc7bf89a5abe?rule=$_2.AUTO",
        "location": "71101 Sch\u00f6naich",
        "date_posted": "31.05.2025",
        "date_scrape": "06/08/2025",
        "title": "Dacia Duster I Laureate 4x4*KLIMA*NAVI*ALLRAD*T\u00dcV*",
        "price": "11999 "
    },
    {
        "id": "3098637029",
        "ad_type": "offer",
        "car_km": "64000 ",
        "car_registration": " 03/2019",
        "image_src": "https://img.kleinanzeigen.de/api/v1/prod-ads/images/14/148e8420-4b83-4236-9258-390bfd00661e?rule=$_2.AUTO",
        "location": "78050 Villingen-\u200bSchwenningen",
        "date_posted": "31.05.2025",
        "date_scrape": "06/08/2025",
        "title": "Dacia Sandero II Stepway Celebration Kamera 1Hand",
        "price": "7499 "
    },
    {
        "id": "3098620353",
        "ad_type": "offer",
        "car_km": "186000 ",
        "car_registration": " 09/2012",
        "image_src": "https://img.kleinanzeigen.de/api/v1/prod-ads/images/26/260023e9-7d0a-47bd-b3fd-4daa3254becd?rule=$_2.AUTO",
        "location": "88250 Weingarten",
        "date_posted": "31.05.2025",
        "date_scrape": "06/08/2025",
        "title": "Dacia Duster 1.6 16V 105 4x2 Essentiel Essentiel",
        "price": "6950 "
    },
    {
        "id": "3098572451",
        "ad_type": "offer",
        "car_km": "69300 ",
        "car_registration": " 05/2018",
        "image_src": "https://img.kleinanzeigen.de/api/v1/prod-ads/images/f8/f8e526c5-f0fb-4577-a425-636c118bfce5?rule=$_2.AUTO",
        "location": "78554 Aldingen",
        "date_posted": "31.05.2025",
        "date_scrape": "06/08/2025",
        "title": "Dacia Sandero II Stepway Essential TCe 90 *Klima",
        "price": "8750 "
    },
    {
        "id": "3098521789",
        "ad_type": "offer",
        "car_km": "69300 ",
        "car_registration": " 04/2019",
        "image_src": "https://img.kleinanzeigen.de/api/v1/prod-ads/images/b6/b6c63ba2-aed6-413e-9c13-88840edc939d?rule=$_2.AUTO",
        "location": "74743 Seckach",
        "date_posted": "31.05.2025",
        "date_scrape": "06/08/2025",
        "title": "Dacia Duster II Prestige 4WD *AHK*",
        "price": "14900 "
    },
    {
        "id": "3098455159",
        "ad_type": "offer",
        "car_km": "106051 ",
        "car_registration": " 07/2019",
        "image_src": "https://img.kleinanzeigen.de/api/v1/prod-ads/images/2b/2b1d9b4d-307f-4a74-91f0-53d4a681c162?rule=$_2.AUTO",
        "location": "77880 Sasbach",
        "date_posted": "31.05.2025",
        "date_scrape": "06/08/2025",
        "title": "Dacia Dokker/Garantie/Scheckheft/1.Hand/AHK/NAVI",
        "price": "13497 "
    }
]