[
    {
        "id": "3047016184",
        "ad_type": "offer",
        "car_km": "69550 ",
        "car_registration": " 07/2019",
        "image_src": "https://img.kleinanzeigen.de/api/v1/prod-ads/images/c2/c2c02595-7178-4c4b-9207-c3d864ad2466?rule=$_2.AUTO",
        "location": "35066 Frankenberg (Eder)",
        "date_posted": "03.04.2025",
        "date_scrape": "04/08/2025",
        "title": "Dacia Sandero II Stepway Prestige TCe 90 eco\u00b2",
        "price": "9990 "
    },
    {
        "id": "3047015998",
        "ad_type": "offer",
        "car_km": "145000 ",
        "car_registration": " 03/2006",
        "image_src": "https://img.kleinanzeigen.de/api/v1/prod-ads/images/07/079c614e-e9df-45fa-bad8-66ff8bfde1d5?rule=$_2.AUTO",
        "location": "16775 L\u00f6wenberger Land",
        "date_posted": "03.04.2025",
        "date_scrape": "04/08/2025",
        "title": "Dacia Logan Laureate",
        "price": "799 "
    },
    {
        "id": "3047014686",
        "ad_type": "offer",
        "car_km": "49800 ",
        "car_registration": " 02/2021",
        "image_src": "https://img.kleinanzeigen.de/api/v1/prod-ads/images/5a/5a6b5a83-6623-4c5f-9028-659124b8f5fb?rule=$_2.AUTO",
        "location": "55252 Mainz-\u200bKastel",
        "date_posted": "03.04.2025",
        "date_scrape": "04/08/2025",
        "title": "Dacia Sandero Stepway Comfort TCe 90",
        "price": "12990 "
    },
    {
        "id": "3047009808",
        "ad_type": "offer",
        "car_km": "54000 ",
        "car_registration": " 05/2019",
        "image_src": "https://img.kleinanzeigen.de/api/v1/prod-ads/images/68/680b1145-e365-4ce1-9012-c7773b59d060?rule=$_2.AUTO",
        "location": "10827 Sch\u00f6neberg",
        "date_posted": "03.04.2025",
        "date_scrape": "04/08/2025",
        "title": "Dacia Dokker Stepway Celebration Navi R\u00fcckfahrkamera",
        "price": "14950 "
    },
    {
        "id": "3047005158",
        "ad_type": "offer",
        "car_km": "104212 ",
        "car_registration": " 07/2018",
        "image_src": "https://img.kleinanzeigen.de/api/v1/prod-ads/images/fa/fa3ab83a-ae8d-43c3-8695-057c670398c1?rule=$_2.AUTO",
        "location": "22529 Hamburg Lokstedt",
        "date_posted": "03.04.2025",
        "date_scrape": "04/08/2025",
        "title": "Dacia Duster II Comfort ABS Fahrerairbag Beifahrerairb",
        "price": "10490 "
    },
    {
        "id": "3047004025",
        "ad_type": "offer",
        "car_km": "100169 ",
        "car_registration": " 06/2018",
        "image_src": "https://img.kleinanzeigen.de/api/v1/prod-ads/images/52/523a84c6-780c-43dd-928a-ab62a8fc79ce?rule=$_2.AUTO",
        "location": "22763 Hamburg Ottensen",
        "date_posted": "03.04.2025",
        "date_scrape": "04/08/2025",
        "title": "Dacia Dokker Dokker SCe 100 Stepway Navi Klima",
        "price": "12750 "
    },
    {
        "id": "3014649499",
        "ad_type": "offer",
        "car_km": "50000 ",
        "car_registration": " 07/2020",
        "image_src": "https://img.kleinanzeigen.de/api/v1/prod-ads/images/e7/e72aedbc-ad03-4d08-a62c-8619f1df806a?rule=$_2.AUTO",
        "location": "58454 Witten",
        "date_posted": "03.04.2025",
        "date_scrape": "04/08/2025",
        "title": "Dacia Sandero II Stepway Essential *1 Hand*LPG Autogas",
        "price": "9900 "
    },
    {
        "id": "2866097334",
        "ad_type": "offer",
        "car_km": "86903 ",
        "car_registration": " 02/2017",
        "image_src": "https://img.kleinanzeigen.de/api/v1/prod-ads/images/22/2280562b-a279-427a-8223-666564e00e83?rule=$_2.AUTO",
        "location": "16766 Kremmen",
        "date_posted": "03.04.2025",
        "date_scrape": "04/08/2025",
        "title": "Dacia Lodgy dCi 110 Stepway, 7Sitzer",
        "price": "12990 "
    },
    {
        "id": "2987517309",
        "ad_type": "offer",
        "car_km": "266500 ",
        "car_registration": " 09/2012",
        "image_src": "https://img.kleinanzeigen.de/api/v1/prod-ads/images/3a/3ada58b1-fe08-4a3d-816b-1faa7af88555?rule=$_2.AUTO",
        "location": "33102 Paderborn",
        "date_posted": "03.04.2025",
        "date_scrape": "04/08/2025",
        "title": "Dacia Lodgy Ambiance",
        "price": "1790 "
    },
    {
        "id": "3047001900",
        "ad_type": "offer",
        "car_km": "30700 ",
        "car_registration": " 10/2022",
        "image_src": "https://img.kleinanzeigen.de/api/v1/prod-ads/images/32/32e5bcb1-8525-4fb3-aaf4-bea0fc524858?rule=$_2.AUTO",
        "location": "54516 Wittlich",
        "date_posted": "03.04.2025",
        "date_scrape": "04/08/2025",
        "title": "Dacia Jogger Extreme+ TCe 100 ECO-G *AHK/Kamera*",
        "price": "17990 "
    },
    {
        "id": "3047001497",
        "ad_type": "offer",
        "car_km": "96000 ",
        "car_registration": " 12/2017",
        "image_src": "https://img.kleinanzeigen.de/api/v1/prod-ads/images/6b/6b71ce2b-933a-44da-9d13-4c93cb588b5b?rule=$_2.AUTO",
        "location": "24145 Meimersdorf-\u200bMoorsee",
        "date_posted": "03.04.2025",
        "date_scrape": "04/08/2025",
        "title": "Dacia Dokker SCe 100 Access",
        "price": "3999 "
    },
    {
        "id": "3035944774",
        "ad_type": "offer",
        "car_km": "85900 ",
        "car_registration": " 06/2013",
        "image_src": "https://img.kleinanzeigen.de/api/v1/prod-ads/images/b3/b3d9ada1-e482-4765-a9d7-9a49cf044448?rule=$_2.AUTO",
        "location": "42651 Solingen",
        "date_posted": "03.04.2025",
        "date_scrape": "04/08/2025",
        "title": "Dacia Sandero Stepway  Prestige dCi90 NAVI KLIMA",
        "price": "6980 "
    },
    {
        "id": "3041861394",
        "ad_type": "offer",
        "car_km": "33400 ",
        "car_registration": " 08/2019",
        "image_src": "https://img.kleinanzeigen.de/api/v1/prod-ads/images/e1/e19eb337-d1bd-42e7-95b0-ab744699ec43?rule=$_2.AUTO",
        "location": "42651 Solingen",
        "date_posted": "03.04.2025",
        "date_scrape": "04/08/2025",
        "title": "Dacia Dokker Stepway NAVI+KLIMA*CAM*PDC 1HD*ALLWETTER",
        "price": "16980 "
    },
    {
        "id": "3041860963",
        "ad_type": "offer",
        "car_km": "38300 ",
        "car_registration": " 04/2020",
        "image_src": "https://img.kleinanzeigen.de/api/v1/prod-ads/images/9e/9eaec783-8d2b-4bd4-909d-d08056ea682c?rule=$_2.AUTO",
        "location": "42651 Solingen",
        "date_posted": "03.04.2025",
        "date_scrape": "04/08/2025",
        "title": "Dacia Dokker Stepway+TCe 130 NAVI+CAM Sitzheizung AHK",
        "price": "17680 "
    },
    {
        "id": "3046999986",
        "ad_type": "offer",
        "car_km": "21603 ",
        "car_registration": " 07/2021",
        "image_src": "https://img.kleinanzeigen.de/api/v1/prod-ads/images/ee/eec650d8-58cc-4164-a18c-d4372cea88e3?rule=$_2.AUTO",
        "location": "29221 Celle",
        "date_posted": "03.04.2025",
        "date_scrape": "04/08/2025",
        "title": "Dacia Duster Urban dCi 115 2WD +NAVI+PDC+Kamera+1.Hand",
        "price": "17390 "
    },
    {
        "id": "3046999383",
        "ad_type": "offer",
        "car_km": "7312 ",
        "car_registration": " 06/2023",
        "image_src": "https://img.kleinanzeigen.de/api/v1/prod-ads/images/96/965984f1-23d0-45f0-ab4c-4b805349e219?rule=$_2.AUTO",
        "location": "51766 Engelskirchen",
        "date_posted": "03.04.2025",
        "date_scrape": "04/08/2025",
        "title": "Dacia Jogger Expression/ 1.HAND/7 SITZE/ PDC/KLIMAAUTO",
        "price": "19799 "
    },
    {
        "id": "3046999024",
        "ad_type": "offer",
        "car_km": "174000 ",
        "car_registration": " 05/2014",
        "image_src": "https://img.kleinanzeigen.de/api/v1/prod-ads/images/1c/1ca71a54-4e47-4e68-b609-a1e62eb52c7f?rule=$_2.AUTO",
        "location": "30179 Nord",
        "date_posted": "03.04.2025",
        "date_scrape": "04/08/2025",
        "title": "Dacia Sandero II Stepway Prestige",
        "price": "4300 "
    },
    {
        "id": "3040013518",
        "ad_type": "offer",
        "car_km": "55798 ",
        "car_registration": " 05/2022",
        "image_src": "https://img.kleinanzeigen.de/api/v1/prod-ads/images/2a/2a127871-62d2-4505-bc35-91b8c33e875c?rule=$_2.AUTO",
        "location": "08223 Neustadt Vogtland",
        "date_posted": "03.04.2025",
        "date_scrape": "04/08/2025",
        "title": "Dacia Logan Comfort TCE 90 CVT",
        "price": "13123 "
    },
    {
        "id": "3046998075",
        "ad_type": "offer",
        "car_km": "167000 ",
        "car_registration": " 11/2015",
        "image_src": "https://img.kleinanzeigen.de/api/v1/prod-ads/images/fd/fd67fdd3-994e-40af-8f8b-5a69fc2138b9?rule=$_2.AUTO",
        "location": "09120 Chemnitz",
        "date_posted": "03.04.2025",
        "date_scrape": "04/08/2025",
        "title": "Dacia Duster  Celebration 4x2\"T\u00dcV\"GARANTIE\"",
        "price": "7499 "
    },
    {
        "id": "3046997711",
        "ad_type": "offer",
        "car_km": "35050 ",
        "car_registration": " 12/2021",
        "image_src": "https://img.kleinanzeigen.de/api/v1/prod-ads/images/09/094079eb-8d9f-4896-be00-7c20e39e1896?rule=$_2.AUTO",
        "location": "33102 Paderborn",
        "date_posted": "03.04.2025",
        "date_scrape": "04/08/2025",
        "title": "Dacia Spring Electric Comfort Plus",
        "price": "6290 "
    },
    {
        "id": "3046997614",
        "ad_type": "offer",
        "car_km": "27900 ",
        "car_registration": " 08/2022",
        "image_src": "https://img.kleinanzeigen.de/api/v1/prod-ads/images/9c/9c57a0ef-baea-4a69-8267-c71770baac95?rule=$_2.AUTO",
        "location": "72355 Sch\u00f6mberg",
        "date_posted": "03.04.2025",
        "date_scrape": "04/08/2025",
        "title": "Dacia Jogger Extreme+ AHK KAMERA",
        "price": "17990 "
    },
    {
        "id": "3046996052",
        "ad_type": "offer",
        "car_km": "159000 ",
        "car_registration": " 02/2018",
        "image_src": "https://img.kleinanzeigen.de/api/v1/prod-ads/images/ec/ec618f61-fa7d-4c55-8fb2-f0de093855dd?rule=$_2.AUTO",
        "location": "33129 Delbr\u00fcck",
        "date_posted": "03.04.2025",
        "date_scrape": "04/08/2025",
        "title": "Dacia Lodgy. 7-Sitzer LPG",
        "price": "6800 "
    },
    {
        "id": "3046994172",
        "ad_type": "offer",
        "car_km": "124126 ",
        "car_registration": " 06/2016",
        "image_src": "https://img.kleinanzeigen.de/api/v1/prod-ads/images/43/43b1ada2-7f0f-488f-8d7b-431f4dd34510?rule=$_2.AUTO",
        "location": "19348 Perleberg",
        "date_posted": "03.04.2025",
        "date_scrape": "04/08/2025",
        "title": "Dacia Sandero II Stepway Prestige/NAVI/PDC/KLIMA/TEMPO",
        "price": "6990 "
    },
    {
        "id": "3046992053",
        "ad_type": "offer",
        "car_km": "111700 ",
        "car_registration": " 10/2006",
        "image_src": "https://img.kleinanzeigen.de/api/v1/prod-ads/images/eb/eb0788e8-cdb4-48a9-ac15-911eaba68669?rule=$_2.AUTO",
        "location": "65604 Elz",
        "date_posted": "03.04.2025",
        "date_scrape": "04/08/2025",
        "title": "Dacia Logan 1.4 MPI Limousine (1 Hand/T\u00dcV 11/2026)",
        "price": "1200 "
    },
    {
        "id": "3046991132",
        "ad_type": "offer",
        "car_km": "39000 ",
        "car_registration": " 06/2020",
        "image_src": "https://img.kleinanzeigen.de/api/v1/prod-ads/images/0f/0f61cd0d-a503-43f8-b171-f2b903a5b0ad?rule=$_2.AUTO",
        "location": "70839 Gerlingen",
        "date_posted": "03.04.2025",
        "date_scrape": "04/08/2025",
        "title": "Dacia Dokker Stepway 131PS EZ: 06/20, KM: 40.000",
        "price": "15990 "
    }
]