{
  "seller_name": "Privater Anbieter",
  "seller_type": "Privater Nutzer",
  "active_since": "Aktiv seit 12.11.2015",
  "Marke": "Dacia",
  "Modell": "Sandero",
  "Kilometerstand": "49.500 km",
  "Fahrzeugzustand": "Unbeschädigtes Fahrzeug",
  "Erstzulassung": "Juni 2019",
  "Kraftstoffart": "Benzin",
  "Leistung": "73 PS",
  "Getriebe": "Manuell",
  "Fahrzeugtyp": "Kleinwagen",
  "Anzahl Türen": "4/5",
  "HU bis": "Juli 2026",
  "Umweltplakette": "4 (Grün)",
  "Schadstoffklasse": "Euro6",
  "Außenfarbe": "Schwarz",
  "extras": [
    "Anhängerkupplung",
    "Leichtmetallfelgen",
    "Klimaanlage",
    "Radio/Tuner",
    "Bluetooth",
    "Freisprecheinrichtung",
    "Tempomat",
    "Antiblockiersystem (ABS)",
    "Scheckheftgepflegt"
  ],
  "description": "Schöner Sandero,Klima, ZV mit Funkschlüssel,elektr. Fenster ,USBBluetoothStart/StopAlufelgenAnhängerkupplungTempomat, ArmlehneNichtraucherKleinwagenGebrauchtfahrzeugHubraum: 999 cm³Anzahl der Türen: 4/5 TürenAnzahl Sitzplätze: 5Schadstoffklasse: Euro6Umweltplakette: 4 (Grün)Anzahl der Fahrzeughalter: 1HU: 7/2026Farbe: SchwarzFarbe (Hersteller): --Innenausstattung: --Farbe der Innenausstattung: --Airbags: Front-, Seiten- und weitere AirbagsAnhängerkupplung: Anhängerkupplung festRadio: Tuner/RadioTagfahrlicht (Art): LED-TagfahrlichtAusstattungABS, Berganfahrassistent, Bluetooth, Bordcomputer, CD-Spieler, ESP, Elektr. Fensterheber, Elektr. Seitenspiegel, Elektr. Wegfahrsperre, Freisprecheinrichtung, Isofix, Isofix Beifahrersitz, Leichtmetallfelgen, Multifunktionslenkrad, Nebelscheinwerfer, Nichtraucher-Fahrzeug, Reifendruckkontrolle, Scheckheftgepflegt, Servolenkung, Soundsystem, Start/Stopp-Automatik, Traktionskontrolle, USB, ZentralverriegelungDer Preis ist Verhandlungsbasis.Privatanbieter67590 MonsheimDeutschlandTel.: +49 151 50715491Inserat bereitgestellt von",
  "title": "Dacia Sandero SCe 75 Comfort, Klima, AHK, Alu",
  "price": "7.499 €",
  "ad_id": "2238028584"
}